twat_os/__init__.py
twat_os/__version__.py
twat_os/paths.py
twat_os/paths.toml
twat_os-2.7.5.dist-info/METADATA
twat_os-2.7.5.dist-info/WHEEL
twat_os-2.7.5.dist-info/entry_points.txt
twat_os-2.7.5.dist-info/licenses/LICENSE
twat_os-2.7.5.dist-info/RECORD
