Metadata-Version: 2.4
Name: twat-os
Version: 2.7.5
Summary: Operating system utilities for twat
Project-URL: Documentation, https://github.com/twardoch/twat-os#readme
Project-URL: Issues, https://github.com/twardoch/twat-os/issues
Project-URL: Source, https://github.com/twardoch/twat-os
Author-email: Adam Twardoch <adam+github@twardoch.com>
License-Expression: MIT
License-File: LICENSE
Keywords: operating-system,os,system,twat,utilities
Classifier: Development Status :: 4 - Beta
Classifier: Intended Audience :: Developers
Classifier: License :: OSI Approved :: MIT License
Classifier: Operating System :: OS Independent
Classifier: Programming Language :: Python
Classifier: Programming Language :: Python :: 3.10
Classifier: Programming Language :: Python :: 3.11
Classifier: Programming Language :: Python :: 3.12
Classifier: Programming Language :: Python :: Implementation :: CPython
Classifier: Programming Language :: Python :: Implementation :: PyPy
Requires-Python: >=3.10
Requires-Dist: fire>=0.6.0
Requires-Dist: loguru>=0.7.2
Requires-Dist: twat>=1.8.1
Provides-Extra: all
Requires-Dist: fire>=0.6.0; extra == 'all'
Requires-Dist: loguru>=0.7.2; extra == 'all'
Requires-Dist: mypy>=1.15.0; extra == 'all'
Requires-Dist: pathlib>=1.0.1; extra == 'all'
Requires-Dist: pre-commit>=4.1.0; extra == 'all'
Requires-Dist: psutil>=5.9.5; extra == 'all'
Requires-Dist: ruff>=0.9.7; extra == 'all'
Requires-Dist: twat>=1.8.1; extra == 'all'
Provides-Extra: dev
Requires-Dist: absolufy-imports>=0.3.1; extra == 'dev'
Requires-Dist: hatch-vcs>=0.4.0; extra == 'dev'
Requires-Dist: hatch>=1.14.0; extra == 'dev'
Requires-Dist: hatchling>=1.27.0; extra == 'dev'
Requires-Dist: isort>=6.0.1; extra == 'dev'
Requires-Dist: mypy>=1.15.0; extra == 'dev'
Requires-Dist: pre-commit>=4.1.0; extra == 'dev'
Requires-Dist: pyupgrade>=3.19.1; extra == 'dev'
Requires-Dist: ruff>=0.9.7; extra == 'dev'
Provides-Extra: docs
Requires-Dist: myst-parser>=3.0.0; extra == 'docs'
Requires-Dist: sphinx-autodoc-typehints>=2.0.0; extra == 'docs'
Requires-Dist: sphinx-rtd-theme>=2.0.0; extra == 'docs'
Requires-Dist: sphinx>=7.2.6; extra == 'docs'
Provides-Extra: test
Requires-Dist: coverage[toml]>=7.6.12; extra == 'test'
Requires-Dist: pytest-asyncio>=0.25.3; extra == 'test'
Requires-Dist: pytest-benchmark[histogram]>=5.1.0; extra == 'test'
Requires-Dist: pytest-cov>=6.0.0; extra == 'test'
Requires-Dist: pytest-mock>=3.14.0; extra == 'test'
Requires-Dist: pytest-timeout>=2.3.1; extra == 'test'
Requires-Dist: pytest-xdist>=3.6.1; extra == 'test'
Requires-Dist: pytest>=8.3.4; extra == 'test'
